{
	"configurations" : 
	[
		{
			"directories" : 
			[
				{
					"build" : ".",
					"hasInstallRule" : true,
					"jsonFile" : "directory-.-Release-ee624c0e165e4454443c.json",
					"minimumCMakeVersion" : 
					{
						"string" : "3.15"
					},
					"projectIndex" : 0,
					"source" : ".",
					"targetIndexes" : 
					[
						0,
						1,
						2
					]
				}
			],
			"name" : "Release",
			"projects" : 
			[
				{
					"directoryIndexes" : 
					[
						0
					],
					"name" : "chomp_motion_planner",
					"targetIndexes" : 
					[
						0,
						1,
						2
					]
				}
			],
			"targets" : 
			[
				{
					"directoryIndex" : 0,
					"id" : "chomp_motion_planner::@6890427a1f51a3e7e1df",
					"jsonFile" : "target-chomp_motion_planner-Release-d8c99cfd65e3e70fa83f.json",
					"name" : "chomp_motion_planner",
					"projectIndex" : 0
				},
				{
					"directoryIndex" : 0,
					"id" : "chomp_motion_planner_uninstall::@6890427a1f51a3e7e1df",
					"jsonFile" : "target-chomp_motion_planner_uninstall-Release-2f4d5fd473bca790ebb7.json",
					"name" : "chomp_motion_planner_uninstall",
					"projectIndex" : 0
				},
				{
					"directoryIndex" : 0,
					"id" : "uninstall::@6890427a1f51a3e7e1df",
					"jsonFile" : "target-uninstall-Release-52c7cbbbca249907646c.json",
					"name" : "uninstall",
					"projectIndex" : 0
				}
			]
		}
	],
	"kind" : "codemodel",
	"paths" : 
	{
		"build" : "/home/fabian/moveit2/build/chomp_motion_planner",
		"source" : "/home/fabian/moveit2/moveit_planners/chomp/chomp_motion_planner"
	},
	"version" : 
	{
		"major" : 2,
		"minor" : 6
	}
}
